wellradpy/__init__.py
wellradpy/drawdown.py
wellradpy/recovery.py
wellradpy/utils.py
wellradpy-2.1.dist-info/LICENSE.txt
wellradpy-2.1.dist-info/METADATA
wellradpy-2.1.dist-info/WHEEL
wellradpy-2.1.dist-info/top_level.txt
wellradpy-2.1.dist-info/RECORD
