Metadata-Version: 2.1
Name: wellradpy
Version: 2.1
Summary: A Python package to calculate the radius of influence and radius of investigation of pumping wells.
Home-page: https://github.com/etiennebresciani/wellradpy
Author: Etienne Bresciani
Keywords: groundwater wells hydraulics
Classifier: Programming Language :: Python :: 2
Classifier: Programming Language :: Python :: 3
Classifier: License :: OSI Approved :: MIT License
Classifier: Operating System :: OS Independent
License-File: LICENSE.txt
Requires-Dist: numpy
Requires-Dist: scipy (>=1.2.0)
